newscatcherapi_client/__init__.py
newscatcherapi_client/api_client.py
newscatcherapi_client/api_response.py
newscatcherapi_client/apis/__init__.py
newscatcherapi_client/apis/path_to_api.py
newscatcherapi_client/apis/paths/__init__.py
newscatcherapi_client/apis/paths/api_authors.py
newscatcherapi_client/apis/paths/api_latest_headlines.py
newscatcherapi_client/apis/paths/api_search.py
newscatcherapi_client/apis/paths/api_search_by_link.py
newscatcherapi_client/apis/paths/api_search_similar.py
newscatcherapi_client/apis/paths/api_sources.py
newscatcherapi_client/apis/paths/api_subscription.py
newscatcherapi_client/apis/tag_to_api.py
newscatcherapi_client/apis/tags/__init__.py
newscatcherapi_client/apis/tags/authors_api.py
newscatcherapi_client/apis/tags/authors_api_generated.py
newscatcherapi_client/apis/tags/authors_api_raw.py
newscatcherapi_client/apis/tags/latest_headlines_api.py
newscatcherapi_client/apis/tags/latest_headlines_api_generated.py
newscatcherapi_client/apis/tags/latest_headlines_api_raw.py
newscatcherapi_client/apis/tags/search_api.py
newscatcherapi_client/apis/tags/search_api_generated.py
newscatcherapi_client/apis/tags/search_api_raw.py
newscatcherapi_client/apis/tags/search_link_api.py
newscatcherapi_client/apis/tags/search_link_api_generated.py
newscatcherapi_client/apis/tags/search_link_api_raw.py
newscatcherapi_client/apis/tags/search_similar_api.py
newscatcherapi_client/apis/tags/search_similar_api_generated.py
newscatcherapi_client/apis/tags/search_similar_api_raw.py
newscatcherapi_client/apis/tags/sources_api.py
newscatcherapi_client/apis/tags/sources_api_generated.py
newscatcherapi_client/apis/tags/sources_api_raw.py
newscatcherapi_client/apis/tags/subscription_api.py
newscatcherapi_client/apis/tags/subscription_api_generated.py
newscatcherapi_client/apis/tags/subscription_api_raw.py
newscatcherapi_client/client.py
newscatcherapi_client/client.pyi
newscatcherapi_client/client_custom.py
newscatcherapi_client/configuration.py
newscatcherapi_python_sdk-6.0.14.dist-info/LICENSE
newscatcherapi_python_sdk-6.0.14.dist-info/METADATA
newscatcherapi_python_sdk-6.0.14.dist-info/WHEEL
newscatcherapi_python_sdk-6.0.14.dist-info/RECORD
